gym_datums/__init__.py
gym_datums/_version.py
gym_datums/envs/__init__.py
gym_datums/envs/portfolio_env.py
gym_datums/wrappers/__init__.py
gym_datums/wrappers/observation_wrappers.py
gym_datums/wrappers/reward_wrappers.py
gym_datums-1.0.1.dist-info/LICENSE
gym_datums-1.0.1.dist-info/METADATA
gym_datums-1.0.1.dist-info/WHEEL
gym_datums-1.0.1.dist-info/top_level.txt
gym_datums-1.0.1.dist-info/RECORD
