Metadata-Version: 2.1
Name: gym-datums
Version: 1.0.1
Summary: Gym environments focused around time series.
Home-page: https://github.com/SwamyDev/gym-datums
License: UNKNOWN
Platform: UNKNOWN
Requires-Dist: gym
Provides-Extra: test
Requires-Dist: pytest ; extra == 'test'
Requires-Dist: pytest-cov ; extra == 'test'
